{
  "schema_version": "iris.collection-run.v2",
  "run_id": "20260715T112745383440Z-4674bc4f",
  "status": "COMPLETE",
  "started_at": "2026-07-15T11:27:45.383549+00:00",
  "completed_at": "2026-07-15T11:28:06.971297+00:00",
  "trajectories": [
    {
      "trajectory_id": "pt_reddit_vote__103102__run_20260715T112745383440Z-4674bc4f",
      "logical_trajectory_id": "pt_reddit_vote__103102",
      "run_id": "20260715T112745383440Z-4674bc4f",
      "task_id": "webarena.27",
      "seed": 0,
      "state_id": "pt_reddit_vote__103102",
      "action_type": "reddit_vote",
      "n_steps": 1,
      "success": true,
      "collector_success": true,
      "traj_success": true,
      "environment_origin": "webarena",
      "environment_family": "webarena",
      "environment_instance": "http://user2-dind:9999",
      "site": "reddit",
      "is_mock": false,
      "n_key_states": 1,
      "code_version": "worktree-sha256:a87439231cadefde81d5bcff846e05d0dd65511675522389c08c0e9b13321e8f",
      "snapshot_compaction": "target_anchored.v1",
      "raw_artifact": "raw/trajectories/pt_reddit_vote__103102__run_20260715T112745383440Z-4674bc4f.jsonl"
    },
    {
      "trajectory_id": "pt_reddit_subscribe__technology__run_20260715T112745383440Z-4674bc4f",
      "logical_trajectory_id": "pt_reddit_subscribe__technology",
      "run_id": "20260715T112745383440Z-4674bc4f",
      "task_id": "webarena.27",
      "seed": 0,
      "state_id": "pt_reddit_subscribe__technology",
      "action_type": "reddit_subscribe",
      "n_steps": 1,
      "success": true,
      "collector_success": true,
      "traj_success": true,
      "environment_origin": "webarena",
      "environment_family": "webarena",
      "environment_instance": "http://user2-dind:9999",
      "site": "reddit",
      "is_mock": false,
      "n_key_states": 1,
      "code_version": "worktree-sha256:a87439231cadefde81d5bcff846e05d0dd65511675522389c08c0e9b13321e8f",
      "snapshot_compaction": "target_anchored.v1",
      "raw_artifact": "raw/trajectories/pt_reddit_subscribe__technology__run_20260715T112745383440Z-4674bc4f.jsonl"
    }
  ],
  "code_version": "worktree-sha256:a87439231cadefde81d5bcff846e05d0dd65511675522389c08c0e9b13321e8f",
  "site": "reddit",
  "state_bank": "raw/state_bank/reddit_key_states.jsonl",
  "meta": "raw/trajectories_meta.jsonl"
}
